complexity_analyzer/__init__.py
complexity_analyzer/analyzer.py
complexity_analyzer/cli.py
complexity_analyzer/profiler.py
complexity_analyzer/utils.py
complexity_analyzer-0.1.0.dist-info/licenses/Licence
complexity_analyzer-0.1.0.dist-info/METADATA
complexity_analyzer-0.1.0.dist-info/WHEEL
complexity_analyzer-0.1.0.dist-info/entry_points.txt
complexity_analyzer-0.1.0.dist-info/top_level.txt
complexity_analyzer-0.1.0.dist-info/RECORD
