Metadata-Version: 2.4
Name: complexity-analyzer
Version: 0.1.0
Summary: A tool to analyze time and space complexity of Python code with visualizations
Home-page: https://github.com/i-soumya18/complexity_analyzer
Author: Soumyaranjan sahoo
Author-email: sahoosoumya242004@gmail.com
Keywords: complexity analysis,big o notation,algorithm,performance,profiling,visualization
Classifier: Programming Language :: Python :: 3
Classifier: License :: OSI Approved :: MIT License
Classifier: Operating System :: OS Independent
Classifier: Topic :: Software Development :: Libraries :: Python Modules
Classifier: Topic :: Software Development :: Testing
Classifier: Intended Audience :: Developers
Classifier: Intended Audience :: Education
Requires-Python: >=3.7
License-File: Licence
Requires-Dist: matplotlib>=3.0.0
Requires-Dist: numpy>=1.18.0
Requires-Dist: scipy>=1.4.0
Dynamic: author
Dynamic: author-email
Dynamic: classifier
Dynamic: description
Dynamic: description-content-type
Dynamic: home-page
Dynamic: keywords
Dynamic: license-file
Dynamic: requires-dist
Dynamic: requires-python
Dynamic: summary
